{
  "tweets": [
    {
      "id": 1,
      "title": "hi i am zahida"
    },
    {
      "id": 2,
      "title": "hi i am aasiff"
    },
    {
      "title": "zahida wani",
      "id": 3
    },
    {
      "title": "zahida wani",
      "id": 4
    },
    {
      "title": "zahida nellofar",
      "id": 5
    },
    {
      "title": "insha",
      "id": 6
    },
    {
      "title": "aaabb",
      "id": 7
    },
    {
      "title": "aaabb",
      "id": 8
    },
    {
      "title": "aaabb",
      "id": 9
    },
    {
      "title": "nnnnn",
      "id": 10
    },
    {
      "title": "nnnnn",
      "id": 11
    },
    {
      "title": "nnnnn",
      "id": 12
    },
    {
      "title": "nnnnn",
      "id": 13
    },
    {
      "title": "nnnnn",
      "id": 14
    },
    {
      "title": "nnnnn",
      "id": 15
    },
    {
      "title": "nnnnn",
      "id": 16
    },
    {
      "title": "nnnnn",
      "id": 17
    }
  ]
}